reaktion/__init__.py
reaktion/actor.py
reaktion/atoms/__init__.py
reaktion/atoms/arkitekt.py
reaktion/atoms/arkitekt_filter.py
reaktion/atoms/base.py
reaktion/atoms/combination/__init__.py
reaktion/atoms/combination/base.py
reaktion/atoms/combination/combinelatest.py
reaktion/atoms/combination/gate.py
reaktion/atoms/combination/withlatest.py
reaktion/atoms/combination/zip.py
reaktion/atoms/errors.py
reaktion/atoms/filter/__init__.py
reaktion/atoms/filter/all.py
reaktion/atoms/generic.py
reaktion/atoms/helpers.py
reaktion/atoms/local.py
reaktion/atoms/operations/__init__.py
reaktion/atoms/operations/base.py
reaktion/atoms/operations/math.py
reaktion/atoms/reactive.py
reaktion/atoms/template.py
reaktion/atoms/transformation/__init__.py
reaktion/atoms/transformation/base.py
reaktion/atoms/transformation/buffer_complete.py
reaktion/atoms/transformation/chunk.py
reaktion/atoms/transformation/filter.py
reaktion/atoms/transformation/split.py
reaktion/atoms/transport.py
reaktion/atoms/utils.py
reaktion/contractors.py
reaktion/engine.py
reaktion/errors.py
reaktion/events.py
reaktion/exceptions.py
reaktion/extension.py
reaktion/plant.py
reaktion/registry.py
reaktion/utils.py
reaktion-0.1.50.dist-info/METADATA
reaktion-0.1.50.dist-info/WHEEL
reaktion-0.1.50.dist-info/RECORD
