Metadata-Version: 2.1
Name: reaktion
Version: 0.1.50
Summary: 
Author: jhnnsrs
Author-email: jhnnsrs@gmail.com
Requires-Python: >=3.8
Classifier: Programming Language :: Python :: 3
Classifier: Programming Language :: Python :: 3.8
Classifier: Programming Language :: Python :: 3.9
Classifier: Programming Language :: Python :: 3.10
Classifier: Programming Language :: Python :: 3.11
Requires-Dist: fluss (>=0.1.59)
Requires-Dist: rekuest (>=0.2.9)
